forgepastebin/__init__.py
forgepastebin/app.py
forgepastebin/version.py
forgepastebin/widgets.py
forgepastebin/controllers/__init__.py
forgepastebin/model/__init__.py
forgepastebin/model/paste.py
forgepastebin/nf/pastebin/css/pygments.css
forgepastebin/nf/pastebin/images/pastebin_24.png
forgepastebin/nf/pastebin/images/pastebin_32.png
forgepastebin/nf/pastebin/images/pastebin_48.png
forgepastebin/templates/new.html
forgepastebin/templates/pastes.html
forgepastebin/templates/paste/paste.html
forgepastebin/templates/paste/paste.js
forgepastebin/templates/widgets/paste_form.html
forgepastebin/tests/__init__.py
forgepastebin/tests/test_functional.py
ForgePastebin-0.8.2.dist-info/METADATA
ForgePastebin-0.8.2.dist-info/WHEEL
ForgePastebin-0.8.2.dist-info/entry_points.txt
ForgePastebin-0.8.2.dist-info/top_level.txt
ForgePastebin-0.8.2.dist-info/zip-safe
ForgePastebin-0.8.2.dist-info/RECORD
