Metadata-Version: 2.1
Name: ForgePastebin
Version: 0.8.2
Summary: Pastebin plugin for the Apache Allura platform
Home-page: http://sf.net/p/forgepastebin
Author: Tim Van Steenburgh
Author-email: tvansteenburgh@geek.net
License: Apache 2.0
Requires-Python: >=3.7
